openapi_spec_validator/__init__.py
openapi_spec_validator/__main__.py
openapi_spec_validator/constructors.py
openapi_spec_validator/decorators.py
openapi_spec_validator/exceptions.py
openapi_spec_validator/factories.py
openapi_spec_validator/generators.py
openapi_spec_validator/handlers.py
openapi_spec_validator/loaders.py
openapi_spec_validator/managers.py
openapi_spec_validator/schemas.py
openapi_spec_validator/shortcuts.py
openapi_spec_validator/validators.py
openapi_spec_validator/resources/schemas/v2.0/schema.json
openapi_spec_validator/resources/schemas/v3.0.0/schema.json
stableforks_openapi_spec_validator-0.2.5.dist-info/LICENSE
stableforks_openapi_spec_validator-0.2.5.dist-info/METADATA
stableforks_openapi_spec_validator-0.2.5.dist-info/WHEEL
stableforks_openapi_spec_validator-0.2.5.dist-info/entry_points.txt
stableforks_openapi_spec_validator-0.2.5.dist-info/top_level.txt
stableforks_openapi_spec_validator-0.2.5.dist-info/RECORD
