Metadata-Version: 2.1
Name: stableforks-openapi-spec-validator
Version: 0.2.5
Summary: UNKNOWN
Home-page: https://github.com/stableforks/stableforks-openapi-spec-validator
Author: Artur Maciag
Author-email: maciag.artur@gmail.com
License: Apache License, Version 2.0
Platform: UNKNOWN
Classifier: Development Status :: 4 - Beta
Classifier: Intended Audience :: Developers
Classifier: Topic :: Software Development :: Libraries :: Python Modules
Classifier: Operating System :: OS Independent
Classifier: Programming Language :: Python :: 2.7
Classifier: Programming Language :: Python :: 3.4
Classifier: Programming Language :: Python :: 3.5
Classifier: Programming Language :: Python :: 3.6
Classifier: Programming Language :: Python :: 3.7
Requires-Dist: jsonschema (<3)
Requires-Dist: PyYAML (>=4.2b1)
Requires-Dist: six
Requires-Dist: pathlib ; python_version == "2.7"
